video_generation_api/__init__.py
video_generation_api/api_client.py
video_generation_api/app.py
video_generation_api/cli.py
video_generation_api/core_functions.py
video_generation_api-1.0.1.dist-info/licenses/LICENSE
video_generation_api-1.0.1.dist-info/METADATA
video_generation_api-1.0.1.dist-info/WHEEL
video_generation_api-1.0.1.dist-info/entry_points.txt
video_generation_api-1.0.1.dist-info/top_level.txt
video_generation_api-1.0.1.dist-info/RECORD
