Metadata-Version: 2.4
Name: video-generation-api
Version: 1.0.1
Summary: A powerful Docker-based API for intelligent video generation with professional effects and subtitles
Home-page: https://github.com/preangelleo/video-generation-docker
Author: Leo Wang
Author-email: Leo Wang <preangelleo@gmail.com>
License: MIT
Project-URL: homepage, https://github.com/preangelleo/video-generation-docker
Project-URL: documentation, https://github.com/preangelleo/video-generation-docker#readme
Project-URL: repository, https://github.com/preangelleo/video-generation-docker
Project-URL: issues, https://github.com/preangelleo/video-generation-docker/issues
Keywords: video,generation,api,docker,flask,moviepy,ffmpeg,subtitles,effects,animation
Classifier: Development Status :: 5 - Production/Stable
Classifier: Intended Audience :: Developers
Classifier: Topic :: Multimedia :: Video
Classifier: Topic :: Multimedia :: Video :: Conversion
Classifier: Topic :: Software Development :: Libraries :: Python Modules
Classifier: License :: OSI Approved :: MIT License
Classifier: Programming Language :: Python :: 3
Classifier: Programming Language :: Python :: 3.8
Classifier: Programming Language :: Python :: 3.9
Classifier: Programming Language :: Python :: 3.10
Classifier: Programming Language :: Python :: 3.11
Classifier: Programming Language :: Python :: 3.12
Classifier: Operating System :: OS Independent
Requires-Python: >=3.8
License-File: LICENSE
Requires-Dist: flask==3.0.0
Requires-Dist: werkzeug==3.0.0
Requires-Dist: moviepy==2.0.0
Requires-Dist: opencv-python==4.8.1.78
Requires-Dist: opencv-python-headless==4.8.1.78
Requires-Dist: numpy==1.26.4
Requires-Dist: Pillow==10.1.0
Requires-Dist: imageio==2.31.5
Requires-Dist: imageio-ffmpeg==0.4.9
Requires-Dist: typing-extensions==4.8.0
Requires-Dist: requests>=2.28.0
Provides-Extra: dev
Requires-Dist: pytest>=7.0.0; extra == "dev"
Requires-Dist: pytest-cov>=4.0.0; extra == "dev"
Requires-Dist: black>=22.0.0; extra == "dev"
Requires-Dist: flake8>=6.0.0; extra == "dev"
Dynamic: author
Dynamic: home-page
Dynamic: license-file
Dynamic: requires-python
